graphrecon.py
graphrecon-1.4.2.dist-info/licenses/LICENSE
graphrecon-1.4.2.dist-info/METADATA
graphrecon-1.4.2.dist-info/WHEEL
graphrecon-1.4.2.dist-info/entry_points.txt
graphrecon-1.4.2.dist-info/top_level.txt
graphrecon-1.4.2.dist-info/RECORD
