Metadata-Version: 2.4
Name: graphrecon
Version: 1.4.2
Summary: Fast async GraphQL endpoint scanner
Author: memirhan
License: MIT
Requires-Python: >=3.9
License-File: LICENSE
Requires-Dist: aiohttp>=3.9.0
Dynamic: author
Dynamic: description
Dynamic: description-content-type
Dynamic: license
Dynamic: license-file
Dynamic: requires-dist
Dynamic: requires-python
Dynamic: summary
